setup.py
Flask_QArgs.egg-info/PKG-INFO
Flask_QArgs.egg-info/SOURCES.txt
Flask_QArgs.egg-info/dependency_links.txt
Flask_QArgs.egg-info/requires.txt
Flask_QArgs.egg-info/top_level.txt
flask_qargs/__init__.py