Metadata-Version: 1.0
Name: Flask-QArgs
Version: 0.0.1
Summary: Flask Query Args Parser, using view decorators.
Home-page: https://www.github.com/wonderbeyond/flask-qargs
Author: Wonder
Author-email: wonderbeyond@gmail.com
License: UNKNOWN
Platform: UNKNOWN
